sumbert/__init__.py
sumbert/configuration_bertabs.py
sumbert/modeling_bertabs.py
sumbert/summarize.py
sumbert/utils_summarization.py
sumbert-1.0.0.dist-info/LICENSE
sumbert-1.0.0.dist-info/METADATA
sumbert-1.0.0.dist-info/WHEEL
sumbert-1.0.0.dist-info/top_level.txt
sumbert-1.0.0.dist-info/RECORD
