Metadata-Version: 2.1
Name: sumbert
Version: 1.0.0
Summary: sumbert: A BERT-based summarizer with a frindly API
Home-page: https://github.com/ptarau/sumbert.git
Author: Paul Tarau
License: Apache
Platform: UNKNOWN
Requires-Dist: transformers
